easunpy/__init__.py
easunpy/__main__.py
easunpy/crc.py
easunpy/discover.py
easunpy/inverter.py
easunpy/isolar.py
easunpy/modbusclient.py
easunpy/utils.py
easunpy/debug/__init__.py
easunpy/debug/isolar_smg_II.py
home_assistant/__init__.py
home_assistant/config_flow.py
home_assistant/sensor.py
easunpy-0.1.0.dist-info/METADATA
easunpy-0.1.0.dist-info/WHEEL
easunpy-0.1.0.dist-info/top_level.txt
easunpy-0.1.0.dist-info/RECORD
